finquotes/__init__.py
finquotes/__main__.py
finquotes/aavantage.py
finquotes/barchart.py
finquotes/cmdline.py
finquotes/csvdata.py
finquotes/localhttp.py
finquotes/mstar.py
finquotes/nasdaq.py
finquotes/network_config.py
finquotes/py.typed
finquotes/quandl.py
finquotes/stooq.py
finquotes/yahoo.py
finquotes/yahooquery.py
finquotes/yfinance.py
finquotes/datareader/__init__.py
finquotes/datareader/stooq.py
finquotes-0.68.0.dist-info/METADATA
finquotes-0.68.0.dist-info/WHEEL
finquotes-0.68.0.dist-info/top_level.txt
finquotes-0.68.0.dist-info/RECORD
