Metadata-Version: 2.4
Name: finquotes
Version: 0.68.0
Summary: Retrieves financial quotes from the web
Author: elmotec
Author-email: elmotec@gmx.com
License-Expression: GPL-3.0
Keywords: stock,quote,quotes,financial,finance,share,common,market
Classifier: Development Status :: 4 - Beta
Classifier: Topic :: Office/Business :: Financial :: Investment
Classifier: Topic :: Software Development :: Libraries :: Python Modules
Classifier: Programming Language :: Python
Requires-Python: <3.15,>=3.11
Requires-Dist: beautifulsoup4>=4.10.0
Requires-Dist: click>=8.0.3
Requires-Dist: python-dateutil>=2.8.2
Requires-Dist: lxml>=5.3
Requires-Dist: requests>=2.27
Requires-Dist: requests-cache>=0.9.1
Requires-Dist: yahooquery>=2.3
Requires-Dist: yfinance[nospam]>=0.2.54
Requires-Dist: pandas-datareader>=0.10.0
Requires-Dist: setuptools>=70.0.0
Provides-Extra: develop
Requires-Dist: bump2version; extra == "develop"
Requires-Dist: build; extra == "develop"
Requires-Dist: colorama; extra == "develop"
Requires-Dist: commitizen; extra == "develop"
Requires-Dist: coverage; extra == "develop"
Requires-Dist: jedi-language-server; extra == "develop"
Requires-Dist: mypy; extra == "develop"
Requires-Dist: pre-commit; extra == "develop"
Requires-Dist: pylint; extra == "develop"
Requires-Dist: pytest; extra == "develop"
Requires-Dist: pytest-cov; extra == "develop"
Requires-Dist: pytest-socket; extra == "develop"
Requires-Dist: pyupgrade; extra == "develop"
Requires-Dist: requests-mock; extra == "develop"
Requires-Dist: ruff; extra == "develop"
Requires-Dist: ruff-lsp; extra == "develop"
Requires-Dist: twine; extra == "develop"
Provides-Extra: types
Requires-Dist: pandas-stubs; extra == "types"
Requires-Dist: types-PyYAML; extra == "types"
Requires-Dist: types-python-dateutil; extra == "types"
Requires-Dist: types-requests; extra == "types"
Requires-Dist: types-requests; extra == "types"
Requires-Dist: types-setuptools; extra == "types"
Requires-Dist: types-ujson; extra == "types"
Provides-Extra: test
Requires-Dist: coverage; extra == "test"
Requires-Dist: pytest; extra == "test"
Requires-Dist: pytest-cov; extra == "test"
Requires-Dist: pytest-socket; extra == "test"
Requires-Dist: requests-mock; extra == "test"
Requires-Dist: pre-commit; extra == "test"
Requires-Dist: pylint; extra == "test"
